[[20,{"SectionID":20,"TravelTime":"659","TravelSpeed":"46","CongestionLevel":"1","DataCollectTime2":"2024-12-31 23:00:03"}],[14,{"SectionID":14,"TravelTime":"139","TravelSpeed":"27","CongestionLevel":"2","DataCollectTime2":"2025-02-27 00:00:02"}],[15,{"SectionID":15,"TravelTime":"593","TravelSpeed":"41","CongestionLevel":"1","DataCollectTime2":"2025-02-27 00:00:02"}],[16,{"SectionID":16,"TravelTime":"771","TravelSpeed":"44","CongestionLevel":"1","DataCollectTime2":"2025-02-27 00:00:03"}],[17,{"SectionID":17,"TravelTime":"152","TravelSpeed":"32","CongestionLevel":"1","DataCollectTime2":"2025-02-27 00:00:03"}],[18,{"SectionID":18,"TravelTime":"671","TravelSpeed":"45","CongestionLevel":"1","DataCollectTime2":"2025-02-27 00:00:03"}],[19,{"SectionID":19,"TravelTime":"792","TravelSpeed":"45","CongestionLevel":"1","DataCollectTime2":"2025-02-27 00:00:03"}],[21,{"SectionID":21,"TravelTime":"101","TravelSpeed":"24","CongestionLevel":"2","DataCollectTime2":"2025-02-27 00:00:03"}],[22,{"SectionID":22,"TravelTime":"559","TravelSpeed":"46","CongestionLevel":"1","DataCollectTime2":"2025-02-27 00:00:04"}],[23,{"SectionID":23,"TravelTime":"150","TravelSpeed":"32","CongestionLevel":"1","DataCollectTime2":"2025-02-27 00:00:04"}],[24,{"SectionID":24,"TravelTime":"1263","TravelSpeed":"46","CongestionLevel":"1","DataCollectTime2":"2025-02-27 00:00:04"}],[44,{"SectionID":44,"TravelTime":"640","TravelSpeed":"49","CongestionLevel":"1","DataCollectTime2":"2025-02-27 00:00:04"}]]